{
  "assetsByChunkName": {
    "vendors~app-account~app-confirmation~app-order": "chunk.e94fae83ca2037f08ed0.js",
    "vendors~app-account~app-checkout": "chunk.af72157bdd78c7619797.js",
    "vendors~app-cart~app-checkout": "chunk.952c90b624de88cf4326.js",
    "admin": [
      "admin.9e456eeffc5b8fa63d6e.js",
      "admin.9e456eeffc5b8fa63d6e.js.map"
    ],
    "app-account": "chunk.f92f1ca23bd218ca0e4b.js",
    "app-checkout": "chunk.0d02c1441b4c56cd7fe7.js",
    "app-confirmation": "chunk.e869b40d4bd5bae326f7.js",
    "checkout": [
      "checkout.34b7701d39f8696356ac.js",
      "checkout.34b7701d39f8696356ac.js.map"
    ],
    "storefront": [
      "storefront.0af8e700b54c96e69e6f.css",
      "storefront.9494536a1f8715f9e053.js",
      "storefront.0af8e700b54c96e69e6f.css.map",
      "storefront.9494536a1f8715f9e053.js.map"
    ],
    "vendors~app-cart": "chunk.d3de5580f0f14e649433.js",
    "vendors~app-order": "chunk.ccbec77e9a5e646cb6c9.js"
  }
}